httpie_api_auth.py
httpie_api_auth-0.3.1.dist-info/LICENSE
httpie_api_auth-0.3.1.dist-info/METADATA
httpie_api_auth-0.3.1.dist-info/WHEEL
httpie_api_auth-0.3.1.dist-info/entry_points.txt
httpie_api_auth-0.3.1.dist-info/top_level.txt
httpie_api_auth-0.3.1.dist-info/RECORD
