Metadata-Version: 2.1
Name: httpie-api-auth
Version: 0.3.1
Summary: ApiAuth plugin for HTTPie.
Home-page: https://github.com/enova/httpie-api-auth
Author: Aidan Coyle
Author-email: packrat386@gmail.com
License: MIT
Download-URL: https://github.com/enova/httpie-api-auth
Platform: UNKNOWN
Classifier: Development Status :: 4 - Beta
Classifier: Programming Language :: Python
Classifier: Intended Audience :: Developers
Classifier: Environment :: Plugins
Classifier: License :: OSI Approved :: MIT License
Classifier: Topic :: Internet :: WWW/HTTP
Classifier: Topic :: Utilities
Requires-Dist: httpie (>=0.7.0)
